{"t": "UDN", "n": "US Dollar (bear)", "sec": "FX", "idx": ["FACTOR"], "mcap": 0, "wr": [0.01176, -0.00634, -0.00904, 0.01235, -0.02757, 0.01799, 0.00536, -0.00373, -0.00053, 0.0, 0.00856, 0.00159, -0.01165, 0.00643, -0.01651, 0.01245, -0.00588, -0.00538, -0.00216, 0.00596, -0.01078, 0.0098, 0.00539, 0.0059, -0.00267, 0.00694, -0.00492, -0.00604, 0.00387, 0.02588, -0.01235, 0.00761, -0.00917, 0.00054, -0.0136, -0.00552, 0.00444, -0.00773, 0.00056, 0.01446, 0.00603, -0.00381, 0.00328, 0.00382, -0.01412, 0.00165, 0.0011, -0.00769, 0.00332, -0.01711], "insider": null, "factor": true, "inst": null, "short": {"fails": 1, "prevFails": 1422, "trend": "falling", "level": "low"}, "ret": {"1w": -1.71, "1m": -2.04, "3m": -1.66, "6m": -2.21, "12m": -1.95}, "vol": 7.2, "beta": 0.29, "ff": {"MKT": 0.0, "SMB": 0.0, "HML": 0.0, "MOM": 0.0}, "flow": {"net1m": -0.078, "net3m": -0.015, "in": 12624813, "out": 14756822, "din": 0, "dout": 1095083}, "fcf": null, "fcfY": null, "opt": null, "mfi": 29.7, "atr": 0.27, "brk": 1, "hl": 8.8, "vr": 1.01, "jump": 0.3, "pvol": null, "regime": "random-walk", "mb": {"DXY": -0.74, "RATE": -0.06}, "drv": "DXY", "ema21d": -1.42, "ema21sig": -0.81, "ema21sl": -0.46, "touch": {"up": {"d": 12.35, "p": 0.06}, "dn": {"d": 0.0, "p": 1.0}}, "odds": {"ema": 0.41, "emaDir": "reclaim", "hi": 0.06, "lo": 1.0, "mean": 0.24, "meanDir": "up", "beat": null, "drift": {"hi": -0.03, "lo": 0.0}, "tmed": {"hi": 166.9, "lo": 0.0}, "condHi": 0.12, "flip": 0.25}, "ev": 0.2, "z": {"val": 1.0, "mom": -0.56, "risk": -0.46, "size": -1.2, "fcf": 0.0, "flow": -0.21, "disloc": -0.03, "mfi": -1.13, "ema": -1.46, "contra": -0.68}, "disloc": -0.03, "contra": {"s": 0.18, "dir": "down", "conf": ["value"]}, "evPct": 50, "alerts": ["breakdown odds 100%", "ATR breakout"], "val": {"pe": null, "fpe": null, "peg": null, "evb": null, "epsg": null, "revg": null, "peSec": null, "evSec": null, "peV": null, "pegV": null, "overall": "n/a", "reason": "No positive trailing earnings \u2014 P/E and PEG not meaningful; judge on EV/EBITDA and cash flow."}, "deps": [{"f": "US dollar", "corr": -0.84, "pcorr": -0.79, "sens": -0.84, "sig": true, "stab": "stable", "dir": "against", "lag": 0, "unexp": false}, {"f": "S&P 500", "corr": 0.48, "pcorr": 0.48, "sens": 0.47, "sig": true, "stab": "stable", "dir": "with", "lag": 0, "unexp": false}, {"f": "nat gas", "corr": 0.38, "pcorr": 0.36, "sens": 0.37, "sig": true, "stab": "stable", "dir": "with", "lag": 0, "unexp": false}, {"f": "10Y yield", "corr": -0.45, "pcorr": -0.33, "sens": -0.44, "sig": true, "stab": "stable", "dir": "against", "lag": 0, "unexp": false}, {"f": "credit (HYG)", "corr": 0.53, "pcorr": 0.32, "sens": 0.53, "sig": true, "stab": "stable", "dir": "with", "lag": 0, "unexp": false}, {"f": "gold", "corr": 0.36, "pcorr": 0.31, "sens": 0.35, "sig": true, "stab": "stable", "dir": "with", "lag": 0, "unexp": false}, {"f": "2s10s slope", "corr": -0.32, "pcorr": -0.24, "sens": -0.32, "sig": true, "stab": "stable", "dir": "against", "lag": 0, "unexp": false}], "macroR2": 73, "secRel": -1.66, "opp": -0.63, "oppPct": 17}